quadcube-1.0.0.dist-info/METADATA
quadcube-1.0.0.dist-info/WHEEL
quadcube-1.0.0.dist-info/license_files/LICENSE
quadcube/__init__.py
quadcube/quadcube.cpython-310-x86_64-linux-gnu.so
quadcube-1.0.0.dist-info/RECORD
