Metadata-Version: 2.1
Name: quadcube
Version: 1.0.0
Classifier: Programming Language :: Rust
Classifier: Programming Language :: Python :: Implementation :: CPython
Classifier: Programming Language :: Python :: Implementation :: PyPy
Requires-Dist: numpy
Requires-Dist: pytest; extra == 'test'
Requires-Dist: black; extra == 'test'
Requires-Dist: isort; extra == 'test'
Provides-Extra: test
License-File: LICENSE
Summary: Python bindings for `pix2vec` for converting between quadcube res15 pixel number to ecliptic unit vectors.
Home-Page: https://github.com/Cosmoglobe/zodipy
Requires-Python: >=3.7
